LICENSE
MANIFEST.in
README.md
setup.py
../LICENSE
../README.md
hsml/__init__.py
hsml/connection.py
hsml/constants.py
hsml/decorators.py
hsml/model.py
hsml/model_registry.py
hsml/tag.py
hsml/util.py
hsml/version.py
hsml/client/__init__.py
hsml/client/auth.py
hsml/client/base.py
hsml/client/exceptions.py
hsml/client/external.py
hsml/client/hopsworks.py
hsml/core/__init__.py
hsml/core/dataset_api.py
hsml/core/model_api.py
hsml/core/model_registry_api.py
hsml/core/native_hdfs_api.py
hsml/engine/__init__.py
hsml/engine/hopsworks_engine.py
hsml/engine/local_engine.py
hsml/engine/model_engine.py
hsml/python/__init__.py
hsml/python/model.py
hsml/python/signature.py
hsml/sklearn/__init__.py
hsml/sklearn/model.py
hsml/sklearn/signature.py
hsml/tensorflow/__init__.py
hsml/tensorflow/model.py
hsml/tensorflow/signature.py
hsml/torch/__init__.py
hsml/torch/model.py
hsml/torch/signature.py
hsml/utils/__init__.py
hsml/utils/column.py
hsml/utils/columnar_schema.py
hsml/utils/model_schema.py
hsml/utils/schema.py
hsml/utils/tensor.py
hsml/utils/tensor_schema.py
hsmltestfix.egg-info/PKG-INFO
hsmltestfix.egg-info/SOURCES.txt
hsmltestfix.egg-info/dependency_links.txt
hsmltestfix.egg-info/requires.txt
hsmltestfix.egg-info/top_level.txt
tests/__init__.py
tests/hsml/__init__.py
tests/hsml/core/__init__.py